pgssret/__init__.py
pgssret/__main__.py
pgssret/exceptions.py
pgssret/sendmail.ps1/README.md
pgssret/sendmail.ps1/sendmail.ps1
pgssret-0.0.1.data/data/share/doc/pgssret/README.md
pgssret-0.0.1.data/data/share/doc/pgssret/sched_prop-action.png
pgssret-0.0.1.data/data/share/doc/pgssret/sched_prop-general.png
pgssret-0.0.1.data/data/share/doc/pgssret/sched_prop-settings.png
pgssret-0.0.1.data/data/share/doc/pgssret/sched_prop-trigger.png
pgssret-0.0.1.data/data/share/doc/pgssret/snap_policy-rep.png
pgssret-0.0.1.data/data/share/doc/pgssret/configs/sample.yaml
pgssret-0.0.1.dist-info/METADATA
pgssret-0.0.1.dist-info/WHEEL
pgssret-0.0.1.dist-info/licenses/COPYING
pgssret-0.0.1.dist-info/RECORD
