Metadata-Version: 2.1
Name: pgssret
Version: 0.0.1
Summary: Get and email pay slips from PGSS
Project-URL: Homepage, https://github.com/ashegoulding/pgss-retriever
Project-URL: Bug Tracker, https://github.com/ashegoulding/pgss-retriever/issues
Author-email: David Timber <dxdt@dev.snart.me>
License-File: COPYING
Classifier: Operating System :: OS Independent
Classifier: Programming Language :: Python :: 3.9
Requires-Python: >=3.9
Requires-Dist: pyyaml
Requires-Dist: requests
